eventplane/__init__.py
eventplane/bus/consumer.py
eventplane/bus/producer.py
eventplane/controller/base.py
eventplane/controller/context.py
eventplane/controller/decision.py
eventplane/controller/runtime.py
eventplane/event/envelope.py
eventplane/event/model.py
eventplane/event/mutate.py
eventplane/event/patch.py
eventplane/models/__init__.py
eventplane/models/base.py
eventplane/projection/runner.py
eventplane/rbac/engine.py
eventplane/rbac/policy.py
eventplane/store/event_store.py
eventplane/utils.py
eventplane-0.1.0.dist-info/METADATA
eventplane-0.1.0.dist-info/WHEEL
eventplane-0.1.0.dist-info/RECORD
